setup.py
test/__init__.py
test/process_launcher.py
test/test_config.py
test/test_file_writing.py
test/test_server.py
test/test_tcp_client.py
test/test_tcp_server.py
test/testcase.py
usher/__init__.py
usher/app.py
usher/config.py
usher/dotdict.py
usher/log.py
usher/server.py
usher/tcp_client.py
usher/tcp_server.py
usher.egg-info/PKG-INFO
usher.egg-info/SOURCES.txt
usher.egg-info/dependency_links.txt
usher.egg-info/entry_points.txt
usher.egg-info/requires.txt
usher.egg-info/top_level.txt