Metadata-Version: 1.0
Name: usher
Version: 0.0.1
Summary: Distributed Lock Implemented in Python
Home-page: https://github.com/lukecampbell/usher/
Author: Luke Campbell
Author-email: lcampbell@asascience.com
License: LICENSE.txt
Platform: UNKNOWN
